message_ix_models/__init__.py
message_ix_models/cli.py
message_ix_models/py.typed
message_ix_models/types.py
message_ix_models/workflow.py
message_ix_models/data/commodity.yaml
message_ix_models/data/emission.yaml
message_ix_models/data/level.yaml
message_ix_models/data/technology.yaml
message_ix_models/data/unit.yaml
message_ix_models/data/alps/granular-techs_cost_comparison_20170831_revAG_SDS_5year.xlsx
message_ix_models/data/alps/solar_wind_intermittency_20170831_5year.xlsx
message_ix_models/data/alps/useful_level_fuel_potential_contribution_20170907_5year.xlsx
message_ix_models/data/buildings/set.yaml
message_ix_models/data/ccs-dac/co2infrastructure_data_leddev.yaml
message_ix_models/data/ccs-dac/co2infrastructure_data_ssp1dev.yaml
message_ix_models/data/ccs-dac/co2infrastructure_data_ssp2dev.yaml
message_ix_models/data/ccs-dac/co2infrastructure_data_ssp3dev.yaml
message_ix_models/data/ccs-dac/co2infrastructure_data_ssp4dev.yaml
message_ix_models/data/ccs-dac/co2infrastructure_data_ssp5dev.yaml
message_ix_models/data/ccs-dac/daccs_setup_data_leddev.yaml
message_ix_models/data/ccs-dac/daccs_setup_data_ssp1dev.yaml
message_ix_models/data/ccs-dac/daccs_setup_data_ssp2dev.yaml
message_ix_models/data/ccs-dac/daccs_setup_data_ssp3dev.yaml
message_ix_models/data/ccs-dac/daccs_setup_data_ssp4dev.yaml
message_ix_models/data/ccs-dac/daccs_setup_data_ssp5dev.yaml
message_ix_models/data/cd_links/unit.yaml
message_ix_models/data/ceds/ceds_cmip7_Aircraft_intlShipping_byfuel_v_2025_03_18.csv
message_ix_models/data/costs/cooling/tech_map.csv
message_ix_models/data/costs/dac/cost_reduction.csv
message_ix_models/data/costs/dac/scenarios_reduction.csv
message_ix_models/data/costs/dac/tech_map.csv
message_ix_models/data/costs/energy/cost_reduction.csv
message_ix_models/data/costs/energy/scenarios_reduction.csv
message_ix_models/data/costs/energy/tech_map.csv
message_ix_models/data/costs/materials/cost_reduction.csv
message_ix_models/data/costs/materials/scenarios_reduction.csv
message_ix_models-2026.1.15.dist-info/licenses/LICENSE
message_ix_models-2026.1.15.dist-info/METADATA
message_ix_models-2026.1.15.dist-info/WHEEL
message_ix_models-2026.1.15.dist-info/entry_points.txt
message_ix_models-2026.1.15.dist-info/top_level.txt
message_ix_models-2026.1.15.dist-info/RECORD
